docwf/__init__.py
docwf/column_parser.py
docwf/docwf.py
docwf/plugins/__init__.py
docwf/plugins/base.py
docwf/plugins/data_gspread.py
docwf/plugins/data_xlsx.py
docwf/plugins/email.py
docwf/plugins/mailmerge.py
docwf/plugins/makepdf.py
docwf/plugins/pdf_watermark.py
docwf/plugins/printsheets.py
docwf/plugins/qr.py
docwf/plugins/split_pdf.py
docwf/plugins/watermark.py
doc_workflow-0.1.1a3.dist-info/LICENSE
doc_workflow-0.1.1a3.dist-info/METADATA
doc_workflow-0.1.1a3.dist-info/WHEEL
doc_workflow-0.1.1a3.dist-info/entry_points.txt
doc_workflow-0.1.1a3.dist-info/top_level.txt
doc_workflow-0.1.1a3.dist-info/RECORD
